edge_srt_to_speech/__init__.py
edge_srt_to_speech/__main__.py
edge_srt_to_speech-0.0.24.dist-info/LICENSE
edge_srt_to_speech-0.0.24.dist-info/METADATA
edge_srt_to_speech-0.0.24.dist-info/WHEEL
edge_srt_to_speech-0.0.24.dist-info/entry_points.txt
edge_srt_to_speech-0.0.24.dist-info/top_level.txt
edge_srt_to_speech-0.0.24.dist-info/RECORD
