Metadata-Version: 2.1
Name: edge-srt-to-speech
Version: 0.0.24
Summary: Use Microsoft Edge's TTS to convert SubRip to speech
Home-page: https://github.com/rany2/edge-srt-to-speech
Author: rany
Author-email: ranygh@riseup.net
Project-URL: Bug Tracker, https://github.com/rany2/edge-srt-to-speech/issues
Classifier: Programming Language :: Python :: 3
Classifier: License :: OSI Approved :: GNU General Public License v3 (GPLv3)
Classifier: Operating System :: OS Independent
Requires-Python: >=3.7
License-File: LICENSE
Requires-Dist: edge-tts==6.1.17
Requires-Dist: pysrt==1.1.2
Requires-Dist: tqdm==4.67.0
Provides-Extra: dev
Requires-Dist: black; extra == "dev"
Requires-Dist: isort; extra == "dev"
Requires-Dist: pylint; extra == "dev"
